[ {
  "id" : "festival-52",
  "name" : "Lễ hội Đống Đa",
  "date" : "5/1",
  "location" : "Hà Nội, quận Đống Đa",
  "relatedHistoricalFigureNames" : [ "Nguyễn Huệ" ],
  "relatedHistoricalFigureIds" : [ ]
}, {
  "id" : "festival-53",
  "name" : "Hội vật Liễu Đôi",
  "date" : "5/1",
  "location" : "Hà Nam, huyện Thanh Liêm",
  "relatedHistoricalFigureNames" : [ "" ],
  "relatedHistoricalFigureIds" : [ ]
}, {
  "id" : "festival-54",
  "name" : "hội Gióng Sóc Sơn",
  "date" : "6/1",
  "location" : "Hà Nội, Sóc Sơn",
  "relatedHistoricalFigureNames" : [ "Thánh Gióng" ],
  "relatedHistoricalFigureIds" : [ ]
}, {
  "id" : "festival-55",
  "name" : "Lễ hội Cổ Loa",
  "date" : "6/1",
  "location" : "Hà Nội, Đông Anh",
  "relatedHistoricalFigureNames" : [ "An Dương Vương" ],
  "relatedHistoricalFigureIds" : [ "figure-44" ]
}, {
  "id" : "festival-56",
  "name" : "Lễ hội chùa Bái Đính",
  "date" : "6/1",
  "location" : "Ninh Bình, Gia Viễn",
  "relatedHistoricalFigureNames" : [ "" ],
  "relatedHistoricalFigureIds" : [ ]
}, {
  "id" : "festival-57",
  "name" : "Chợ Viềng",
  "date" : "7/1",
  "location" : "Nam Định, Vụ Bản",
  "relatedHistoricalFigureNames" : [ "" ],
  "relatedHistoricalFigureIds" : [ ]
}, {
  "id" : "festival-58",
  "name" : "Lễ hội đầm Ô Loan",
  "date" : "7/1",
  "location" : "Phú Yên, Ô Loan",
  "relatedHistoricalFigureNames" : [ "" ],
  "relatedHistoricalFigureIds" : [ ]
}, {
  "id" : "festival-59",
  "name" : "Đại lễ Đức Chí Tôn",
  "date" : "9/1",
  "location" : "Tây Ninh, Đạo Cao Đài",
  "relatedHistoricalFigureNames" : [ "Đức Chí Tôn" ],
  "relatedHistoricalFigureIds" : [ ]
}, {
  "id" : "festival-60",
  "name" : "Hội xuân Yên Tử",
  "date" : "10/1",
  "location" : "Quảng Ninh, núi Yên Tử",
  "relatedHistoricalFigureNames" : [ "Trần Nhân Tông" ],
  "relatedHistoricalFigureIds" : [ ]
}, {
  "id" : "festival-61",
  "name" : "Hội phết Hiền Quan",
  "date" : "13/1",
  "location" : "Phú Thọ, huyện Tam Nông",
  "relatedHistoricalFigureNames" : [ "Thiều Hoa công chúa", "Mộc trang đại vương" ],
  "relatedHistoricalFigureIds" : [ ]
}, {
  "id" : "festival-62",
  "name" : "Hội Lim",
  "date" : "13/1",
  "location" : "Bắc Ninh, huyện Tiên Du",
  "relatedHistoricalFigureNames" : [ "Nguyễn Đình Diễn" ],
  "relatedHistoricalFigureIds" : [ ]
}, {
  "id" : "festival-63",
  "name" : "Lễ hội chùa Hương",
  "date" : "6/1",
  "location" : "Hà Nội, huyện Mỹ Đức",
  "relatedHistoricalFigureNames" : [ "Quan Thế Âm Bồ Tát" ],
  "relatedHistoricalFigureIds" : [ ]
}, {
  "id" : "festival-64",
  "name" : "Hội chùa Côn Sơn",
  "date" : "15/1",
  "location" : "Hải Dương, huyện Chí Linh",
  "relatedHistoricalFigureNames" : [ "Huyền Quang", "Nguyễn Trãi" ],
  "relatedHistoricalFigureIds" : [ ]
}, {
  "id" : "festival-65",
  "name" : "Lễ hội làm chay",
  "date" : "14/1",
  "location" : "Long An, thị trấn Tầm Vu",
  "relatedHistoricalFigureNames" : [ "Đỗ Tường Phong", "Đỗ Tường Tự" ],
  "relatedHistoricalFigureIds" : [ ]
}, {
  "id" : "festival-66",
  "name" : "Tết Nguyên tiêu",
  "date" : "15/1",
  "location" : "Nhiều quốc gia",
  "relatedHistoricalFigureNames" : [ "" ],
  "relatedHistoricalFigureIds" : [ ]
}, {
  "id" : "festival-67",
  "name" : "Lễ hội chọi trâu",
  "date" : "16/1",
  "location" : "Vĩnh Phúc, huyện Lập Thạch",
  "relatedHistoricalFigureNames" : [ "" ],
  "relatedHistoricalFigureIds" : [ ]
}, {
  "id" : "festival-68",
  "name" : "Hội Xuân núi Bà",
  "date" : "4/1",
  "location" : "Tây Ninh, Núi Bà Đen",
  "relatedHistoricalFigureNames" : [ "Linh Sơn Thánh Mẫu" ],
  "relatedHistoricalFigureIds" : [ ]
}, {
  "id" : "festival-69",
  "name" : "Lễ hội đình Yên Phụ",
  "date" : "10/2",
  "location" : "Hà Nội, Hồ Tây",
  "relatedHistoricalFigureNames" : [ "Uy Linh Lang", "Vương Duy", "Vương Ba" ],
  "relatedHistoricalFigureIds" : [ ]
}, {
  "id" : "festival-70",
  "name" : "Lễ hội Miếu Mạch Lũng",
  "date" : "10/2",
  "location" : "Hà Nội, Đông Anh",
  "relatedHistoricalFigureNames" : [ "Minh Mỗ Đại vương Thượng đẳng thần" ],
  "relatedHistoricalFigureIds" : [ ]
}, {
  "id" : "festival-71",
  "name" : "Lễ hội Quán Thế Âm",
  "date" : "19/2",
  "location" : "Đà Nẵng, Ngũ Hành Sơn",
  "relatedHistoricalFigureNames" : [ "Quán Thế Âm Bồ Tát" ],
  "relatedHistoricalFigureIds" : [ ]
}, {
  "id" : "festival-72",
  "name" : "Tiết Thanh minh",
  "date" : "",
  "location" : "",
  "relatedHistoricalFigureNames" : [ "" ],
  "relatedHistoricalFigureIds" : [ ]
}, {
  "id" : "festival-73",
  "name" : "Hội đua voi",
  "date" : "",
  "location" : "Tây Nguyên",
  "relatedHistoricalFigureNames" : [ "" ],
  "relatedHistoricalFigureIds" : [ ]
}, {
  "id" : "festival-74",
  "name" : "Tết Hàn thực",
  "date" : "3/3",
  "location" : "",
  "relatedHistoricalFigureNames" : [ "Giới Tử Thôi", "Tấn Văn Công" ],
  "relatedHistoricalFigureIds" : [ ]
}, {
  "id" : "festival-75",
  "name" : "Hội Phủ Giầy",
  "date" : "3/3",
  "location" : "Nam Định, Vụ Bản",
  "relatedHistoricalFigureNames" : [ "Mẫu Liễu Hạnh" ],
  "relatedHistoricalFigureIds" : [ ]
}, {
  "id" : "festival-76",
  "name" : "Lễ hội Điện Hòn Chén",
  "date" : "2/3",
  "location" : "Thừa Thiên Huế, huyện Hương Trà",
  "relatedHistoricalFigureNames" : [ "Thiên Y A Na" ],
  "relatedHistoricalFigureIds" : [ ]
}, {
  "id" : "festival-77",
  "name" : "Lễ hội Chùa Thầy",
  "date" : "3/3",
  "location" : "Hà Tây, Quốc Oai",
  "relatedHistoricalFigureNames" : [ "Từ Đạo Hạnh" ],
  "relatedHistoricalFigureIds" : [ ]
}, {
  "id" : "festival-78",
  "name" : "Lễ hội Hoa Lư",
  "date" : "6/3",
  "location" : "Ninh Bình, huyện Hoa Lư",
  "relatedHistoricalFigureNames" : [ "Đinh Bộ Lĩnh" ],
  "relatedHistoricalFigureIds" : [ ]
}, {
  "id" : "festival-79",
  "name" : "Lễ hội đền Thái Vi",
  "date" : "14/3",
  "location" : "Ninh Bình, huyện Hoa Lư",
  "relatedHistoricalFigureNames" : [ "Trần Thái Tông", "Trần Thánh Tông", "Trần Nhân Tông", "Trần Anh Tông", "Hiển Từ Hoàng Thái Hậu" ],
  "relatedHistoricalFigureIds" : [ ]
}, {
  "id" : "festival-80",
  "name" : "Lễ hội Nam Trì",
  "date" : "8/3",
  "location" : "Hưng Yên, huyện Ân Thi",
  "relatedHistoricalFigureNames" : [ "Lang Công", "Bảo Công", "Công chúa Hùng vương Lâu nương" ],
  "relatedHistoricalFigureIds" : [ ]
}, {
  "id" : "festival-81",
  "name" : "Giỗ tổ Hùng Vương",
  "date" : "10/3",
  "location" : "Nhiều nơi ở Việt Nam",
  "relatedHistoricalFigureNames" : [ "Vua Hùng" ],
  "relatedHistoricalFigureIds" : [ ]
}, {
  "id" : "festival-82",
  "name" : "Lễ hội đền Mẫu",
  "date" : "10/3",
  "location" : "Hưng Yên, Phố Hiến",
  "relatedHistoricalFigureNames" : [ "Dương Quý Phi" ],
  "relatedHistoricalFigureIds" : [ ]
}, {
  "id" : "festival-83",
  "name" : "Lễ hội Làng cá Cát Bà",
  "date" : "",
  "location" : "Hải Phòng, huyện Cát Hải, Thị trấn Cát Bà",
  "relatedHistoricalFigureNames" : [ "Hồ Chí Minh" ],
  "relatedHistoricalFigureIds" : [ ]
}, {
  "id" : "festival-84",
  "name" : "Hội Gióng Phù Đổng",
  "date" : "7/4",
  "location" : "Hà Nội, huyện Gia Lâm",
  "relatedHistoricalFigureNames" : [ "Thánh Gióng" ],
  "relatedHistoricalFigureIds" : [ ]
}, {
  "id" : "festival-85",
  "name" : "Lễ Phật Đản",
  "date" : "8/4",
  "location" : "Nhiều quốc gia",
  "relatedHistoricalFigureNames" : [ "Phật Tất Đạt Đa" ],
  "relatedHistoricalFigureIds" : [ ]
}, {
  "id" : "festival-86",
  "name" : "Lễ hội Chol Chnam Thmay",
  "date" : "14/4",
  "location" : "Nam Bộ",
  "relatedHistoricalFigureNames" : [ "" ],
  "relatedHistoricalFigureIds" : [ ]
}, {
  "id" : "festival-87",
  "name" : "Lễ khao lề thế lính",
  "date" : "18/3",
  "location" : "Quảng Ngãi, huyện Lý Sơn",
  "relatedHistoricalFigureNames" : [ "" ],
  "relatedHistoricalFigureIds" : [ ]
}, {
  "id" : "festival-88",
  "name" : "Lễ hội miếu Bà Chúa Xứ",
  "date" : "23/4",
  "location" : "Miếu Bà Chúa Xứ, Núi Sam, An Giang, Châu Đốc",
  "relatedHistoricalFigureNames" : [ "Bà Chúa Xứ" ],
  "relatedHistoricalFigureIds" : [ ]
}, {
  "id" : "festival-89",
  "name" : "Tết Đoan ngọ",
  "date" : "5/5",
  "location" : "Nhiều quốc gia",
  "relatedHistoricalFigureNames" : [ "" ],
  "relatedHistoricalFigureIds" : [ ]
}, {
  "id" : "festival-90",
  "name" : "Thất Tịch",
  "date" : "7/7",
  "location" : "Nhiều quốc gia",
  "relatedHistoricalFigureNames" : [ "Ngưu Lang", "Chức Nữ" ],
  "relatedHistoricalFigureIds" : [ ]
}, {
  "id" : "festival-91",
  "name" : "Lễ Vu Lan, Tết Trung Nguyên",
  "date" : "15/7",
  "location" : "Nhiều quốc gia",
  "relatedHistoricalFigureNames" : [ "Bồ tát Mục Liên" ],
  "relatedHistoricalFigureIds" : [ ]
}, {
  "id" : "festival-92",
  "name" : "Lễ hội Nghinh Ông (Quan Thánh Đế Quân)",
  "date" : "",
  "location" : "Phan Thiết (Bình Thuận)",
  "relatedHistoricalFigureNames" : [ "" ],
  "relatedHistoricalFigureIds" : [ ]
}, {
  "id" : "festival-93",
  "name" : "Lễ hội Katê",
  "date" : "",
  "location" : "Bình Thuận",
  "relatedHistoricalFigureNames" : [ "" ],
  "relatedHistoricalFigureIds" : [ ]
}, {
  "id" : "festival-94",
  "name" : "Lễ hội chọi trâu",
  "date" : "9/8",
  "location" : "Hải Phòng, Đồ Sơn",
  "relatedHistoricalFigureNames" : [ "" ],
  "relatedHistoricalFigureIds" : [ ]
}, {
  "id" : "festival-95",
  "name" : "Tết Trung Thu",
  "date" : "15/8",
  "location" : "Nhiều quốc gia",
  "relatedHistoricalFigureNames" : [ "Hằng Nga", "Hậu Nghệ", "Đường Minh Hoàng", "Chú Cuội" ],
  "relatedHistoricalFigureIds" : [ ]
}, {
  "id" : "festival-96",
  "name" : "Hội Đền Kiếp Bạc",
  "date" : "15/8",
  "location" : "Hải Dương, huyện Chí Linh",
  "relatedHistoricalFigureNames" : [ "Trần Hưng Đạo" ],
  "relatedHistoricalFigureIds" : [ ]
}, {
  "id" : "festival-97",
  "name" : "Hội Yến Diêu Trì",
  "date" : "15/8",
  "location" : "Tây Ninh, Tòa Thánh Tây Ninh",
  "relatedHistoricalFigureNames" : [ "Cao Quỳnh Cư", "Phạm Công Tắc", "Cao Hoài Sang", "Nguyễn Thị Hiếu" ],
  "relatedHistoricalFigureIds" : [ ]
}, {
  "id" : "festival-98",
  "name" : "Lễ hội Nghinh Ông (Cá Voi)",
  "date" : "",
  "location" : "Bình Thuận, Tiền Giang",
  "relatedHistoricalFigureNames" : [ "" ],
  "relatedHistoricalFigureIds" : [ ]
}, {
  "id" : "festival-99",
  "name" : "Lễ hội AHDT Nguyễn Trung Trực",
  "date" : "",
  "location" : "Rạch Giá, Kiên Giang",
  "relatedHistoricalFigureNames" : [ "Nguyễn Trung Trực" ],
  "relatedHistoricalFigureIds" : [ ]
}, {
  "id" : "festival-100",
  "name" : "Lễ hội Chùa Keo",
  "date" : "13/9",
  "location" : "Thái Bình, Vũ Thư",
  "relatedHistoricalFigureNames" : [ "Thiền sư Không Lộ" ],
  "relatedHistoricalFigureIds" : [ ]
}, {
  "id" : "festival-101",
  "name" : "Tết cơm mới",
  "date" : "15/10",
  "location" : "Nhiều quốc gia",
  "relatedHistoricalFigureNames" : [ "" ],
  "relatedHistoricalFigureIds" : [ ]
}, {
  "id" : "festival-102",
  "name" : "Lễ hội đền Nguyễn Công Trứ",
  "date" : "13/11",
  "location" : "Ninh Bình, huyện Kim Sơn",
  "relatedHistoricalFigureNames" : [ "Nguyễn Công Trứ" ],
  "relatedHistoricalFigureIds" : [ ]
}, {
  "id" : "festival-103",
  "name" : "Tiễn Ông Táo về trời",
  "date" : "23/12",
  "location" : "Nhiều quốc gia",
  "relatedHistoricalFigureNames" : [ "Thổ Công", "Thổ địa", "Thổ kỳ" ],
  "relatedHistoricalFigureIds" : [ ]
} ]